{
  "ID": "azure_cis_v200_2_1_13",
  "Title": "Ensure that Microsoft Defender Recommendation for 'Apply system updates' status is 'Completed'",
  "Description": "Ensure that the latest OS patches for all virtual machines are applied.",
  "Query": null,
  "ManualVerification": true,
  "Severity": "high",
  "Tags": {
    "category": [
      "Compliance"
    ],
    "cis": [
      "true"
    ],
    "cis_item_id": [
      "2.1.13"
    ],
    "cis_level": [
      "1"
    ],
    "cis_section_id": [
      "2.1"
    ],
    "cis_type": [
      "manual"
    ],
    "cis_version": [
      "v2.0.0"
    ],
    "plugin": [
      "azure"
    ],
    "service": [
      "Azure/SecurityCenter"
    ]
  },
  "Managed": true
}