{
  "ID": 5,
  "Query": {
    "ID": "aws_insight_ebs_volume_unattached",
    "Engine": "odysseus-v0.0.1",
    "QueryToExecute": "select volume_id, volume_type, account_id, kaytu_account_id, kaytu_resource_id\nfrom\n  aws_ebs_volume\nwhere\n  jsonb_array_length(attachments) = 0;",
    "Connector": "AWS",
    "PrimaryTable": "aws_ebs_volume",
    "ListOfTables": [
      "aws_ebs_volume"
    ]
  },
  "Connector": "AWS",
  "ShortTitle": "Unused EBS Disks",
  "LongTitle": "List of unattached EBS volumes",
  "Description": "List of unattached EBS volumes",
  "LogoURL": "",
  "Tags": {
    "category": [
      "Technical Debt",
      "Cost Management"
    ]
  },
  "Links": null,
  "Enabled": true,
  "Internal": false
}