{
  "ID": "azure_synapse_workspace_data_exfiltration_protection_enabled",
  "Engine": "odysseus-v0.0.1",
  "QueryToExecute": "select\n  s.id as resource,\n  case\n    when managed_virtual_network_settings -\u003e\u003e 'preventDataExfiltration' = 'true' then 'ok'\n    else 'alarm'\n  end as status,\n  case\n    when managed_virtual_network_settings -\u003e\u003e 'preventDataExfiltration' = 'true' then s.title || ' data exfiltration protection enabled.'\n    else s.title || ' data exfiltration protection disabled.'\n  end as reason\n  \n  , s.resource_group as resource_group\n  , sub.display_name as subscription\nfrom\n  azure_synapse_workspace as s,\n  azure_subscription as sub\nwhere\n  sub.subscription_id = s.subscription_id;\n",
  "Connector": "Azure",
  "PrimaryTable": "azure_synapse_workspace",
  "ListOfTables": [
    "azure_subscription",
    "azure_synapse_workspace"
  ]
}