{
  "ID": "aws_elasticache_redis_cluster_automatic_backup_retention_15_days",
  "Engine": "odysseus-v0.0.1",
  "QueryToExecute": "select\n  arn as resource,\n  case\n    when snapshot_retention_limit \u003c 15 then 'alarm'\n    else 'ok'\n  end as status,\n  case\n    when snapshot_retention_limit = 0 then title || ' automatic backups not enabled.'\n    when snapshot_retention_limit \u003c 15 then title || ' automatic backup retention period is less than 15 days.'\n    else title || ' automatic backup retention period is more than 15 days.'\n  end as reason\n  , region, account_id\nfrom\n  aws_elasticache_replication_group;\n",
  "Connector": "AWS",
  "PrimaryTable": "aws_elasticache_replication_group",
  "ListOfTables": [
    "aws_elasticache_replication_group"
  ]
}