{
  "ID": "aws_ec2_ami_restrict_public_access",
  "Engine": "odysseus-v0.0.1",
  "QueryToExecute": "select\n  'arn:' || partition || ':ec2:' || region || ':' || account_id || ':image/' || image_id as resource,\n  case\n    when public then 'alarm'\n    else 'ok'\n  end status,\n  case\n    when public then title || ' publicly accessible.'\n    else title || ' not publicly accessible.'\n  end reason\n  \n  , region, account_id\nfrom\n  aws_ec2_ami;\n",
  "Connector": "AWS",
  "PrimaryTable": "aws_ec2_ami",
  "ListOfTables": [
    "aws_ec2_ami"
  ]
}